wrg.py
wrg-0.1.4.dist-info/LICENSE.txt
wrg-0.1.4.dist-info/METADATA
wrg-0.1.4.dist-info/WHEEL
wrg-0.1.4.dist-info/top_level.txt
wrg-0.1.4.dist-info/RECORD
